external_resources/__init__.py
external_resources/__init__.py~
external_resources/cache.py
external_resources/cache.py~
external_resources/checksums.py
external_resources/lockfile.py
external_resources/main.py
external_resources/operations.py
external_resources/options.py
external_resources/registry.py
external_resources/requirements.py
external_resources/tools.py
external_resources-0.4.0.dist-info/licenses/LICENSE
external_resources-0.4.0.dist-info/WHEEL
external_resources-0.4.0.dist-info/entry_points.txt
external_resources-0.4.0.dist-info/METADATA
external_resources-0.4.0.dist-info/RECORD
