Metadata-Version: 2.4
Name: external-resources
Version: 0.4.0
Summary: Fetch and deploy external resources (CSS, JS, Fonts) for web services
Keywords: js,JavaScript,CSS,fonts,vendoring,web application,resources,web,installation
Author: Detlef Lannert
Author-email: Detlef Lannert <detlef@lannert.de>
License-Expression: GPL-3.0-or-later
License-File: LICENSE
Classifier: Development Status :: 4 - Beta
Classifier: Framework :: Django
Classifier: Intended Audience :: Developers
Classifier: License :: OSI Approved :: MIT License
Classifier: Operating System :: POSIX :: Linux
Classifier: Programming Language :: Python :: 3
Classifier: Programming Language :: Python :: 3.10
Classifier: Programming Language :: Python :: 3.11
Classifier: Programming Language :: Python :: 3.12
Classifier: Programming Language :: Python :: 3.13
Classifier: Topic :: Internet :: WWW/HTTP :: HTTP Servers
Classifier: Topic :: Software Development :: Build Tools
Classifier: Typing :: Typed
Requires-Dist: cyclopts
Requires-Dist: httpx
Requires-Dist: msgspec
Requires-Dist: pyyaml
Requires-Dist: packaging
Requires-Dist: pyproject-parser
Requires-Dist: rich
Requires-Dist: tomli-w
Requires-Dist: xdg-base-dirs>=6.0.2
Requires-Dist: uuid7>=0.1.0
Requires-Dist: niquests>=3.15.2
Maintainer: Detlef Lannert
Maintainer-email: Detlef Lannert <detlef@lannert.de>
Requires-Python: >=3.10
Project-URL: Changelog, https://github.com/detlefla/external_resources/blob/master/CHANGELOG.md
Project-URL: Homepage, https://github.com/detlefla/external_resources
Project-URL: Issues, https://github.com/detlefla/external_resources/issues
Project-URL: Repository, https://github.com/detlefla/external_resources.git
